expm/CONFIG
expm/VERSION
expm/__init__.py
expm/common.py
expm/expm.py
expm/expm_common.py
expmcc-0.2.1.dist-info/METADATA
expmcc-0.2.1.dist-info/WHEEL
expmcc-0.2.1.dist-info/entry_points.txt
expmcc-0.2.1.dist-info/top_level.txt
expmcc-0.2.1.dist-info/RECORD
