Metadata-Version: 2.1
Name: expmcc
Version: 0.2.1
Summary: EXPand the Macro when compiling C/C++ files
Home-page: https://github.com/xieby1/expm
Author: xieby1
Author-email: xieby1@outlook.com
License: UNKNOWN
Keywords: c/c++,compiler,macro expansion
Platform: UNKNOWN
